{"title":"Hot sexy big boobed brunette MILF slut gets tied and spanked","uid":8516135,"size":50198777,"categoryP":"porn","categoryS":"movie_clips","magnet":"?xt=urn:btih:1f3ed965f4a1b3c3d0b10b579e96badfbcf77d94&amp;dn=Hot+sexy+big+boobed+brunette+MILF+slut+gets+tied+and+spanked&amp;tr=udp%3A%2F%2Ftracker.openbittorrent.com%3A80&amp;tr=udp%3A%2F%2Fopen.demonii.com%3A1337&amp;tr=udp%3A%2F%2Ftracker.coppersurfer.tk%3A6969&amp;tr=udp%3A%2F%2Fexodus.desync.com%3A6969","seeders":0,"leechers":1,"uploader":"pornophil","files":1,"time":1369740288,"description":"Title: Hot sexy big boobed brunette MILF slut gets tied and spanked thne cunt fingered and fucked  by huge dildo \nResolution: 640x480\nDuration: 00:06:17\nSize: 47.9 MB\n\nScreenshot: &lt;a href=&quot;\nhttp://www.picdumper.com/scr/ac5f74fd75db5e071b0c74969005aceb&quot; rel=&quot;nofollow&quot; target=&quot;_NEW&quot;&gt;\nhttp://www.picdumper.com/scr/ac5f74fd75db5e071b0c74969005aceb&lt;/a&gt;\n\nPreview index: &lt;a href=&quot;\nhttp://www.picdumper.com/idx/ac5f74fd75db5e071b0c74969005aceb&quot; rel=&quot;nofollow&quot; target=&quot;_NEW&quot;&gt;\nhttp://www.picdumper.com/idx/ac5f74fd75db5e071b0c74969005aceb&lt;/a&gt;\n","torrent":{"xt":"urn:btih:1f3ed965f4a1b3c3d0b10b579e96badfbcf77d94","amp;dn":"Hot+sexy+big+boobed+brunette+MILF+slut+gets+tied+and+spanked","amp;tr":["udp%3A%2F%2Ftracker.openbittorrent.com%3A80","udp%3A%2F%2Fopen.demonii.com%3A1337","udp%3A%2F%2Ftracker.coppersurfer.tk%3A6969","udp%3A%2F%2Fexodus.desync.com%3A6969"],"infoHash":"1f3ed965f4a1b3c3d0b10b579e96badfbcf77d94","infoHashBuffer":{"type":"Buffer","data":[31,62,217,101,244,161,179,195,208,177,11,87,158,150,186,223,188,247,125,148]},"announce":[],"urlList":[]}}