{"title":"Mackenzee Pierce - Fill My Position","uid":7945780,"size":476319242,"categoryP":"porn","categoryS":"movie_clips","magnet":"?xt=urn:btih:1fd2547425a88662470a9d2798005faede5e27bf&amp;dn=Mackenzee+Pierce+-+Fill+My+Position&amp;tr=udp%3A%2F%2Ftracker.openbittorrent.com%3A80&amp;tr=udp%3A%2F%2Fopen.demonii.com%3A1337&amp;tr=udp%3A%2F%2Ftracker.coppersurfer.tk%3A6969&amp;tr=udp%3A%2F%2Fexodus.desync.com%3A6969","seeders":0,"leechers":2,"uploader":"irealu69","files":-1,"time":1356124003,"description":"Mackenzee Pierce - Fill My Position\n~~~~~~~~~~~~~~~~~~~~~~~~~~~~~~~~~~~\n\nScreenshots:\n~~~~~~~~~~~~\n &lt;a href=&quot;\nhttp://picturevip.com/x/clean/C1d&quot; rel=&quot;nofollow&quot; target=&quot;_NEW&quot;&gt;\nhttp://picturevip.com/x/clean/C1d&lt;/a&gt;\n &lt;a href=&quot;\nhttp://picturevip.com/x/clean/C1p&quot; rel=&quot;nofollow&quot; target=&quot;_NEW&quot;&gt;\nhttp://picturevip.com/x/clean/C1p&lt;/a&gt;\n &lt;a href=&quot;\nhttp://picturevip.com/x/clean/C1E&quot; rel=&quot;nofollow&quot; target=&quot;_NEW&quot;&gt;\nhttp://picturevip.com/x/clean/C1E&lt;/a&gt;\n &lt;a href=&quot;\nhttp://picturevip.com/x/clean/C1Q&quot; rel=&quot;nofollow&quot; target=&quot;_NEW&quot;&gt;\nhttp://picturevip.com/x/clean/C1Q&lt;/a&gt;\n &lt;a href=&quot;\nhttp://picturevip.com/x/clean/C1U&quot; rel=&quot;nofollow&quot; target=&quot;_NEW&quot;&gt;\nhttp://picturevip.com/x/clean/C1U&lt;/a&gt;\n\n\nVideos Info:\n~~~~~~~~~~~~\nSize: 454.25 MB\nDuration: 28:30\nResolution: 854x480","torrent":{"xt":"urn:btih:1fd2547425a88662470a9d2798005faede5e27bf","amp;dn":"Mackenzee+Pierce+-+Fill+My+Position","amp;tr":["udp%3A%2F%2Ftracker.openbittorrent.com%3A80","udp%3A%2F%2Fopen.demonii.com%3A1337","udp%3A%2F%2Ftracker.coppersurfer.tk%3A6969","udp%3A%2F%2Fexodus.desync.com%3A6969"],"infoHash":"1fd2547425a88662470a9d2798005faede5e27bf","infoHashBuffer":{"type":"Buffer","data":[31,210,84,116,37,168,134,98,71,10,157,39,152,0,95,174,222,94,39,191]},"announce":[],"urlList":[]}}