{"title":"inside.mma.2012.12.17.hdtv.x264-kyr.mp4","uid":7937406,"size":342046070,"categoryP":"video","categoryS":"tv_shows","magnet":"?xt=urn:btih:23b0cdfa53dff9d2dacdb338e0f701b7bc0cfee5&amp;dn=inside.mma.2012.12.17.hdtv.x264-kyr.mp4&amp;tr=udp%3A%2F%2Ftracker.openbittorrent.com%3A80&amp;tr=udp%3A%2F%2Fopen.demonii.com%3A1337&amp;tr=udp%3A%2F%2Ftracker.coppersurfer.tk%3A6969&amp;tr=udp%3A%2F%2Fexodus.desync.com%3A6969","seeders":0,"leechers":1,"uploader":"Strajow","files":1,"time":1355896883,"description":"title Inside MMA\n            genre Talk\n        rel. date 12/18/2012                 format x264\n         air date 12/17/2012                 source HDTV\n          runtime 47mn 57s 140ms            bitrate 839kbps\n         filesize 342046070                 resolu. 720x406\n         frames 29.970\n         audio 2 ch AA\n                                                                    \n         This week, Inside MMA looks forward to the new year.              \n         UFC Middleweight Michael Bisping joins Kenny Rice and Bas Rutten  \n         live to make his case for a shot at the king of the division,     \n         Anderson Silva. Also, UFC fighter Tim Boetsch on his ascent in    \n         the middleweight ranks, Bellator CEO Bjorn Rebney on the future   \n         of his organization and Ron Krucks update on the Cleveland       \n         Clinics brain injury study.                  ","torrent":{"xt":"urn:btih:23b0cdfa53dff9d2dacdb338e0f701b7bc0cfee5","amp;dn":"inside.mma.2012.12.17.hdtv.x264-kyr.mp4","amp;tr":["udp%3A%2F%2Ftracker.openbittorrent.com%3A80","udp%3A%2F%2Fopen.demonii.com%3A1337","udp%3A%2F%2Ftracker.coppersurfer.tk%3A6969","udp%3A%2F%2Fexodus.desync.com%3A6969"],"infoHash":"23b0cdfa53dff9d2dacdb338e0f701b7bc0cfee5","infoHashBuffer":{"type":"Buffer","data":[35,176,205,250,83,223,249,210,218,205,179,56,224,247,1,183,188,12,254,229]},"announce":[],"urlList":[]}}