{"title":"TAYLOR VIXEN, SPENCER SCOTT - PERSUADING AN AUDITOR - 14.06.2013","uid":8573834,"size":93486377,"categoryP":"porn","categoryS":"pictures","magnet":"?xt=urn:btih:328a36608fe7c2139cd846d8c8d4f404dceb0369&amp;dn=TAYLOR+VIXEN%2C+SPENCER+SCOTT+-+PERSUADING+AN+AUDITOR+-+14.06.2013&amp;tr=udp%3A%2F%2Ftracker.openbittorrent.com%3A80&amp;tr=udp%3A%2F%2Fopen.demonii.com%3A1337&amp;tr=udp%3A%2F%2Ftracker.coppersurfer.tk%3A6969&amp;tr=udp%3A%2F%2Fexodus.desync.com%3A6969","seeders":0,"leechers":2,"uploader":"manam69","files":100,"time":1371229838,"description":" &lt;a href=&quot;http://i.imgur.com/aVd5E2i.png&quot; rel=&quot;nofollow&quot; target=&quot;_NEW&quot;&gt;http://i.imgur.com/aVd5E2i.png&lt;/a&gt;\n\nTAYLOR VIXEN, SPENCER SCOTT - PERSUADING AN AUDITOR - 14.06.2013 MaNaM -","torrent":{"xt":"urn:btih:328a36608fe7c2139cd846d8c8d4f404dceb0369","amp;dn":"TAYLOR+VIXEN%2C+SPENCER+SCOTT+-+PERSUADING+AN+AUDITOR+-+14.06.2013","amp;tr":["udp%3A%2F%2Ftracker.openbittorrent.com%3A80","udp%3A%2F%2Fopen.demonii.com%3A1337","udp%3A%2F%2Ftracker.coppersurfer.tk%3A6969","udp%3A%2F%2Fexodus.desync.com%3A6969"],"infoHash":"328a36608fe7c2139cd846d8c8d4f404dceb0369","infoHashBuffer":{"type":"Buffer","data":[50,138,54,96,143,231,194,19,156,216,70,216,200,212,244,4,220,235,3,105]},"announce":[],"urlList":[]}}