{"title":"ShesAFreak.Shae.Snow.Workout.Wanking.XxX","uid":8562851,"size":2396505673,"categoryP":"porn","categoryS":"hd___movies","magnet":"?xt=urn:btih:3d15003079f9c9b59a95f5554a0421db05737872&amp;dn=ShesAFreak.Shae.Snow.Workout.Wanking.XxX&amp;tr=udp%3A%2F%2Ftracker.openbittorrent.com%3A80&amp;tr=udp%3A%2F%2Fopen.demonii.com%3A1337&amp;tr=udp%3A%2F%2Ftracker.coppersurfer.tk%3A6969&amp;tr=udp%3A%2F%2Fexodus.desync.com%3A6969","seeders":0,"leechers":1,"uploader":"handsome_hulk1253","files":1,"time":1370931070,"description":"Screenshots\n &lt;a href=&quot;\nhttp://adultxpictures.com/xxx/df9&quot; rel=&quot;nofollow&quot; target=&quot;_NEW&quot;&gt;\nhttp://adultxpictures.com/xxx/df9&lt;/a&gt; &lt;a href=&quot;\nhttp://adultxpictures.com/xxx/dfv&quot; rel=&quot;nofollow&quot; target=&quot;_NEW&quot;&gt;\nhttp://adultxpictures.com/xxx/dfv&lt;/a&gt; &lt;a href=&quot;\nhttp://adultxpictures.com/xxx/dfy&quot; rel=&quot;nofollow&quot; target=&quot;_NEW&quot;&gt;\nhttp://adultxpictures.com/xxx/dfy&lt;/a&gt;","torrent":{"xt":"urn:btih:3d15003079f9c9b59a95f5554a0421db05737872","amp;dn":"ShesAFreak.Shae.Snow.Workout.Wanking.XxX","amp;tr":["udp%3A%2F%2Ftracker.openbittorrent.com%3A80","udp%3A%2F%2Fopen.demonii.com%3A1337","udp%3A%2F%2Ftracker.coppersurfer.tk%3A6969","udp%3A%2F%2Fexodus.desync.com%3A6969"],"infoHash":"3d15003079f9c9b59a95f5554a0421db05737872","infoHashBuffer":{"type":"Buffer","data":[61,21,0,48,121,249,201,181,154,149,245,85,74,4,33,219,5,115,120,114]},"announce":[],"urlList":[]}}