{"title":"Girl Walks Into a Bar (2012) BR2DVD nl subs NLtoppers","uid":7877925,"size":2971989827,"categoryP":"video","categoryS":"movies_dvdr","magnet":"?xt=urn:btih:550733ce4574fba90ca4c38d083c0e9a7e99ed3c&amp;dn=Girl+Walks+Into+a+Bar+%282012%29+BR2DVD+nl+subs+NLtoppers&amp;tr=udp%3A%2F%2Ftracker.openbittorrent.com%3A80&amp;tr=udp%3A%2F%2Fopen.demonii.com%3A1337&amp;tr=udp%3A%2F%2Ftracker.coppersurfer.tk%3A6969&amp;tr=udp%3A%2F%2Fexodus.desync.com%3A6969","seeders":0,"leechers":2,"uploader":"ChickieChicken","files":-1,"time":1354399687,"description":"The Movie ______ Girl Walks into a Bar (2011) ______\n &lt;a href=&quot;\nhttp://www.moviemeter.nl/film/75407&quot; rel=&quot;nofollow&quot; target=&quot;_NEW&quot;&gt;\nhttp://www.moviemeter.nl/film/75407&lt;/a&gt;\n\nVerenigde Staten\nKomedie / Drama\n80 minuten\n\ngeregisseerd door Sebastian Gutierrez\nmet Carla Gugino, Zachary Quinto en Josh Hartnett\n\nDe voormalige undercover-agente Francine Driver, die zich voordoet als een huurmoordenaar, ontmoet een tandarts in een bar in Los Angels. Zijn naam is Nick en hij wil zijn vrouw dood hebben. Hij heeft echter niet de benodigde vooruitbetaling van $20.000 voorhanden maar belooft dat hij die vannacht nog kan regelen. Als Nick vertrekt ontmoet Francine dejongeman Henry die haar verleidt, om er uiteindelijk met haar portemonnee vandoor te gaan. In haar portemonnee zit belastend bewijsmateriaal, namelijk het opname apparaat waarmee ze het gesprek met Nick heeft opgenomen. Dan begint ze aan een verwoede zoektocht in de bars en clubs van Los Angeles..\n\n================================================================================\n\n\nMovie..............: Girl Walks into a Bar (2011) \nGenre..............: Komedie / Drama\nSource.............: Girl.Walks.Into.A.Bar.2011.1080p.BluRay.x264-iFPD\nRuntime............: 80 min.\nFormat.............: DVDR\nMenu...............: Nope\nVideo..............: Mpeg.Enc.@.2.Pass\nAudio..............: Engels DD 5.1 \nSubtitles.NL.......: Vertaald door: Jos40, Granny, Jolly, Suurtje en Paddy, Heel goed, Klasse job *****\nControle...........: Granny \nBewerking+Resync...: Granny, thanx m8innetje\n\n\n================================================================================\n &lt;a href=&quot;\nhttp://www.imdb.com/title/tt1682246/&quot; rel=&quot;nofollow&quot; target=&quot;_NEW&quot;&gt;\nhttp://www.imdb.com/title/tt1682246/&lt;/a&gt;\n\nA sharp-witted comedy that follows a group of apparent strangers in interlocking stories taking place in ten different bars during the course of one evening throughout Los Angeles. \n\n\n\nBy Chickie","torrent":{"xt":"urn:btih:550733ce4574fba90ca4c38d083c0e9a7e99ed3c","amp;dn":"Girl+Walks+Into+a+Bar+%282012%29+BR2DVD+nl+subs+NLtoppers","amp;tr":["udp%3A%2F%2Ftracker.openbittorrent.com%3A80","udp%3A%2F%2Fopen.demonii.com%3A1337","udp%3A%2F%2Ftracker.coppersurfer.tk%3A6969","udp%3A%2F%2Fexodus.desync.com%3A6969"],"infoHash":"550733ce4574fba90ca4c38d083c0e9a7e99ed3c","infoHashBuffer":{"type":"Buffer","data":[85,7,51,206,69,116,251,169,12,164,195,141,8,60,14,154,126,153,237,60]},"announce":[],"urlList":[]}}