{"title":"wb-df83","uid":7816112,"size":2837324222,"categoryP":"porn","categoryS":"movies","magnet":"?xt=urn:btih:551ccc6c08532262755d92109b2b33566ab74023&amp;dn=wb-df83&amp;tr=udp%3A%2F%2Ftracker.openbittorrent.com%3A80&amp;tr=udp%3A%2F%2Fopen.demonii.com%3A1337&amp;tr=udp%3A%2F%2Ftracker.coppersurfer.tk%3A6969&amp;tr=udp%3A%2F%2Fexodus.desync.com%3A6969","seeders":0,"leechers":0,"uploader":"shae2005","files":2,"time":1352665681,"description":"WB-DF83\nDouble Feature\nWB-DF83-1\nBailey, Haley Paige, Jenaveve Jolie, \nKatja Kassin, Sandra Romain, \nSunny Lane, Tiana Lynn\nMP4\n2:09:48\n640x480\n1.47gbs\n\nWB-DF83-2\nScene 1. Laly, Tristan Segal \nScene 2. Cathy Heaven, girl, guy \nScene 3. Breanne Benson, Chayse Evans, guy \nScene 4. Gina Lynn, girl, Laly \nScene 5. Tarra White, 2 guys \nScene 6. Aleska Diamond, Aletta Ocean, 2 guys\nAVI\n1:37:30\n640x272\n1.16gbs\nPreview\n","torrent":{"xt":"urn:btih:551ccc6c08532262755d92109b2b33566ab74023","amp;dn":"wb-df83","amp;tr":["udp%3A%2F%2Ftracker.openbittorrent.com%3A80","udp%3A%2F%2Fopen.demonii.com%3A1337","udp%3A%2F%2Ftracker.coppersurfer.tk%3A6969","udp%3A%2F%2Fexodus.desync.com%3A6969"],"infoHash":"551ccc6c08532262755d92109b2b33566ab74023","infoHashBuffer":{"type":"Buffer","data":[85,28,204,108,8,83,34,98,117,93,146,16,155,43,51,86,106,183,64,35]},"announce":[],"urlList":[]}}