{"title":"Naruto-Shippuden EPs from 1 - 288 ArabicSub","uid":7817059,"size":37016964467,"categoryP":"video","categoryS":"hd___tv_shows","magnet":"?xt=urn:btih:565e17199a3a4ab0ea8abd24627cec6b198cdf2d&amp;dn=Naruto-Shippuden+EPs+from+1+-+288+ArabicSub&amp;tr=udp%3A%2F%2Ftracker.openbittorrent.com%3A80&amp;tr=udp%3A%2F%2Fopen.demonii.com%3A1337&amp;tr=udp%3A%2F%2Ftracker.coppersurfer.tk%3A6969&amp;tr=udp%3A%2F%2Fexodus.desync.com%3A6969","seeders":0,"leechers":0,"uploader":"magical_99","files":180,"time":1352701329,"description":"Naruto Shippuden EPs from 1 - 288 ArabicSub\n","torrent":{"xt":"urn:btih:565e17199a3a4ab0ea8abd24627cec6b198cdf2d","amp;dn":"Naruto-Shippuden+EPs+from+1+-+288+ArabicSub","amp;tr":["udp%3A%2F%2Ftracker.openbittorrent.com%3A80","udp%3A%2F%2Fopen.demonii.com%3A1337","udp%3A%2F%2Ftracker.coppersurfer.tk%3A6969","udp%3A%2F%2Fexodus.desync.com%3A6969"],"infoHash":"565e17199a3a4ab0ea8abd24627cec6b198cdf2d","infoHashBuffer":{"type":"Buffer","data":[86,94,23,25,154,58,74,176,234,138,189,36,98,124,236,107,25,140,223,45]},"announce":[],"urlList":[]}}