{"title":"Stuff Hors-Serie - Juillet/Aout 2013 [FRENCH]","uid":8649453,"size":106553052,"categoryP":"other","categoryS":"e_books","magnet":"?xt=urn:btih:768d71258d9938b6d6c927381fe8e73a92c16406&amp;dn=Stuff+Hors-Serie+-+Juillet%2FAout+2013+%5BFRENCH%5D&amp;tr=udp%3A%2F%2Ftracker.openbittorrent.com%3A80&amp;tr=udp%3A%2F%2Fopen.demonii.com%3A1337&amp;tr=udp%3A%2F%2Ftracker.coppersurfer.tk%3A6969&amp;tr=udp%3A%2F%2Fexodus.desync.com%3A6969","seeders":0,"leechers":1,"uploader":"lozloz2000","files":-1,"time":1373065919,"description":"Stuff Hors-Serie - Juillet/Aout 2013 (No. 30)\n\n\n\n\n                 Francais | PDF | 100 pages | 102 Mb","torrent":{"xt":"urn:btih:768d71258d9938b6d6c927381fe8e73a92c16406","amp;dn":"Stuff+Hors-Serie+-+Juillet%2FAout+2013+%5BFRENCH%5D","amp;tr":["udp%3A%2F%2Ftracker.openbittorrent.com%3A80","udp%3A%2F%2Fopen.demonii.com%3A1337","udp%3A%2F%2Ftracker.coppersurfer.tk%3A6969","udp%3A%2F%2Fexodus.desync.com%3A6969"],"infoHash":"768d71258d9938b6d6c927381fe8e73a92c16406","infoHashBuffer":{"type":"Buffer","data":[118,141,113,37,141,153,56,182,214,201,39,56,31,232,231,58,146,193,100,6]},"announce":[],"urlList":[]}}