{"title":"Batman Begins [1080p]","uid":7848237,"size":1724148573,"categoryP":"video","categoryS":"hd___movies","magnet":"?xt=urn:btih:83d77c8e8ebdabfc287b2856036bee780c271110&amp;dn=Batman+Begins+%5B1080p%5D&amp;tr=udp%3A%2F%2Ftracker.openbittorrent.com%3A80&amp;tr=udp%3A%2F%2Fopen.demonii.com%3A1337&amp;tr=udp%3A%2F%2Ftracker.coppersurfer.tk%3A6969&amp;tr=udp%3A%2F%2Fexodus.desync.com%3A6969","seeders":0,"leechers":0,"uploader":"sahil1033","files":2,"time":1353526726,"description":"Batman Begins with English subtitles in Full HD (1080p).\nIf you like my work, please do comment.\n\n_____________________________________________________________________________________\n-------------------------------------------------------------------------------------\n\nResolution    : 1920*800\nVideo bitrate : 1574 Kbps\nAudio bitrate : 64 Kbps\nFrame rate    : 23 fps\n_____________________________________________________________________________________\n-------------------------------------------------------------------------------------\n &lt;a href=&quot;\nhttp://www.sahilsingh.in&quot; rel=&quot;nofollow&quot; target=&quot;_NEW&quot;&gt;\nhttp://www.sahilsingh.in&lt;/a&gt;\n\nSeed and enjoy !!","torrent":{"xt":"urn:btih:83d77c8e8ebdabfc287b2856036bee780c271110","amp;dn":"Batman+Begins+%5B1080p%5D","amp;tr":["udp%3A%2F%2Ftracker.openbittorrent.com%3A80","udp%3A%2F%2Fopen.demonii.com%3A1337","udp%3A%2F%2Ftracker.coppersurfer.tk%3A6969","udp%3A%2F%2Fexodus.desync.com%3A6969"],"infoHash":"83d77c8e8ebdabfc287b2856036bee780c271110","infoHashBuffer":{"type":"Buffer","data":[131,215,124,142,142,189,171,252,40,123,40,86,3,107,238,120,12,39,17,16]},"announce":[],"urlList":[]}}