{"title":"Shemale - Vintage - Olivia Love in a Threesome.avi","uid":7925898,"size":126711808,"categoryP":"porn","categoryS":"movie_clips","magnet":"?xt=urn:btih:90586db5ec6a80ef31e2f21a51012e51cd55b3f8&amp;dn=Shemale+-+Vintage+-+Olivia+Love+in+a+Threesome.avi&amp;tr=udp%3A%2F%2Ftracker.openbittorrent.com%3A80&amp;tr=udp%3A%2F%2Fopen.demonii.com%3A1337&amp;tr=udp%3A%2F%2Ftracker.coppersurfer.tk%3A6969&amp;tr=udp%3A%2F%2Fexodus.desync.com%3A6969","seeders":0,"leechers":1,"uploader":"ibxxxxxxxxxx","files":1,"time":1355581496,"description":"Shemale - Vintage - Olivia Love in a Threesome.avi\n\nHot Vintage Shemale Action\n\nEarly Olivia Love - Rare Stuff!!!\n\nOlivia is at it again. Discreetly giving her boyfriend a blowjob, his friend walks in and joins in the fun.\n\nOlivia gets nailed by both plus a few big loads of man-muck.\n\n14 Minutes\n352 X 288\n\nMessage Me if the File Needs to be Re-Seeded\n\nPlease Keep Seeding after Download\n\nStarring\n\nOlivia Love (Vintage) &lt;a href=&quot;\nhttp://postimage.org/image/bul9bzw8t/&quot; rel=&quot;nofollow&quot; target=&quot;_NEW&quot;&gt;\nhttp://postimage.org/image/bul9bzw8t/&lt;/a&gt;\n\n\nScreenshots &lt;a href=&quot;\nhttp://postimage.org/gallery/7la5grry/&quot; rel=&quot;nofollow&quot; target=&quot;_NEW&quot;&gt;\nhttp://postimage.org/gallery/7la5grry/&lt;/a&gt;\n","torrent":{"xt":"urn:btih:90586db5ec6a80ef31e2f21a51012e51cd55b3f8","amp;dn":"Shemale+-+Vintage+-+Olivia+Love+in+a+Threesome.avi","amp;tr":["udp%3A%2F%2Ftracker.openbittorrent.com%3A80","udp%3A%2F%2Fopen.demonii.com%3A1337","udp%3A%2F%2Ftracker.coppersurfer.tk%3A6969","udp%3A%2F%2Fexodus.desync.com%3A6969"],"infoHash":"90586db5ec6a80ef31e2f21a51012e51cd55b3f8","infoHashBuffer":{"type":"Buffer","data":[144,88,109,181,236,106,128,239,49,226,242,26,81,1,46,81,205,85,179,248]},"announce":[],"urlList":[]}}