{"title":"24 S01 (Tv series) com legendas ptbr","uid":7826534,"size":3798955129,"categoryP":"video","categoryS":"tv_shows","magnet":"?xt=urn:btih:9bf3a8c196da1870d577648a7cc062a89247a7ad&amp;dn=24+S01+%28Tv+series%29+com+legendas+ptbr&amp;tr=udp%3A%2F%2Ftracker.openbittorrent.com%3A80&amp;tr=udp%3A%2F%2Fopen.demonii.com%3A1337&amp;tr=udp%3A%2F%2Ftracker.coppersurfer.tk%3A6969&amp;tr=udp%3A%2F%2Fexodus.desync.com%3A6969","seeders":0,"leechers":1,"uploader":"heitorcruv","files":49,"time":1352941415,"description":"Primeira temporada de 24 horas legendada","torrent":{"xt":"urn:btih:9bf3a8c196da1870d577648a7cc062a89247a7ad","amp;dn":"24+S01+%28Tv+series%29+com+legendas+ptbr","amp;tr":["udp%3A%2F%2Ftracker.openbittorrent.com%3A80","udp%3A%2F%2Fopen.demonii.com%3A1337","udp%3A%2F%2Ftracker.coppersurfer.tk%3A6969","udp%3A%2F%2Fexodus.desync.com%3A6969"],"infoHash":"9bf3a8c196da1870d577648a7cc062a89247a7ad","infoHashBuffer":{"type":"Buffer","data":[155,243,168,193,150,218,24,112,213,119,100,138,124,192,98,168,146,71,167,173]},"announce":[],"urlList":[]}}