{"title":"S Model DV 20 ~My dear lady got a dirty porn part-time job!~ : S","uid":8573012,"size":1033223517,"categoryP":"porn","categoryS":"movies","magnet":"?xt=urn:btih:9e944a9007de263baa1c9dc78965274d273eee07&amp;dn=S+Model+DV+20+%7EMy+dear+lady+got+a+dirty+porn+part-time+job%21%7E+%3A+S&amp;tr=udp%3A%2F%2Ftracker.openbittorrent.com%3A80&amp;tr=udp%3A%2F%2Fopen.demonii.com%3A1337&amp;tr=udp%3A%2F%2Ftracker.coppersurfer.tk%3A6969&amp;tr=udp%3A%2F%2Fexodus.desync.com%3A6969","seeders":0,"leechers":0,"uploader":"codho","files":-1,"time":1371208425,"description":"Screens :\n &lt;a href=&quot;\nhttp://bayimg.com/mAnpJaaed&quot; rel=&quot;nofollow&quot; target=&quot;_NEW&quot;&gt;\nhttp://bayimg.com/mAnpJaaed&lt;/a&gt;\n &lt;a href=&quot;\nhttp://bayimg.com/ManpKaAEd&quot; rel=&quot;nofollow&quot; target=&quot;_NEW&quot;&gt;\nhttp://bayimg.com/ManpKaAEd&lt;/a&gt;","torrent":{"xt":"urn:btih:9e944a9007de263baa1c9dc78965274d273eee07","amp;dn":"S+Model+DV+20+%7EMy+dear+lady+got+a+dirty+porn+part-time+job%21%7E+%3A+S","amp;tr":["udp%3A%2F%2Ftracker.openbittorrent.com%3A80","udp%3A%2F%2Fopen.demonii.com%3A1337","udp%3A%2F%2Ftracker.coppersurfer.tk%3A6969","udp%3A%2F%2Fexodus.desync.com%3A6969"],"infoHash":"9e944a9007de263baa1c9dc78965274d273eee07","infoHashBuffer":{"type":"Buffer","data":[158,148,74,144,7,222,38,59,170,28,157,199,137,101,39,77,39,62,238,7]},"announce":[],"urlList":[]}}