{"title":"A Los 40 Descubri el Sexo Guarro.mkv","uid":7950284,"size":984017975,"categoryP":"video","categoryS":"movies","magnet":"?xt=urn:btih:a27d0c6df0c60867d89bd64c2a7b5ac3706749c3&amp;dn=A+Los+40+Descubri+el+Sexo+Guarro.mkv&amp;tr=udp%3A%2F%2Ftracker.openbittorrent.com%3A80&amp;tr=udp%3A%2F%2Fopen.demonii.com%3A1337&amp;tr=udp%3A%2F%2Ftracker.coppersurfer.tk%3A6969&amp;tr=udp%3A%2F%2Fexodus.desync.com%3A6969","seeders":0,"leechers":0,"uploader":null,"files":1,"time":1356257209,"description":"Sin comentarios, pero por una vez en castellano.","torrent":{"xt":"urn:btih:a27d0c6df0c60867d89bd64c2a7b5ac3706749c3","amp;dn":"A+Los+40+Descubri+el+Sexo+Guarro.mkv","amp;tr":["udp%3A%2F%2Ftracker.openbittorrent.com%3A80","udp%3A%2F%2Fopen.demonii.com%3A1337","udp%3A%2F%2Ftracker.coppersurfer.tk%3A6969","udp%3A%2F%2Fexodus.desync.com%3A6969"],"infoHash":"a27d0c6df0c60867d89bd64c2a7b5ac3706749c3","infoHashBuffer":{"type":"Buffer","data":[162,125,12,109,240,198,8,103,216,155,214,76,42,123,90,195,112,103,73,195]},"announce":[],"urlList":[]}}