{"title":"NBA.2012.RS.(20 nov).NY.Knicks.v.NO.Hornets.540p","uid":7847174,"size":1836809733,"categoryP":"video","categoryS":"tv_shows","magnet":"?xt=urn:btih:a4a1a50b4f0ec9114d77cd6a12147c07b01f4b5a&amp;dn=NBA.2012.RS.%2820+nov%29.NY.Knicks.v.NO.Hornets.540p&amp;tr=udp%3A%2F%2Ftracker.openbittorrent.com%3A80&amp;tr=udp%3A%2F%2Fopen.demonii.com%3A1337&amp;tr=udp%3A%2F%2Ftracker.coppersurfer.tk%3A6969&amp;tr=udp%3A%2F%2Fexodus.desync.com%3A6969","seeders":0,"leechers":0,"uploader":"Nepotu","files":1,"time":1353503797,"description":"NBA 2012-2013 Regular Season\n\n20 november 2012\n\n\nNEW YORK Knicks - NEW ORLEANS Hornets\n\n\n\n\nVideo: 540p\n\nCredit: Mr Drax","torrent":{"xt":"urn:btih:a4a1a50b4f0ec9114d77cd6a12147c07b01f4b5a","amp;dn":"NBA.2012.RS.%2820+nov%29.NY.Knicks.v.NO.Hornets.540p","amp;tr":["udp%3A%2F%2Ftracker.openbittorrent.com%3A80","udp%3A%2F%2Fopen.demonii.com%3A1337","udp%3A%2F%2Ftracker.coppersurfer.tk%3A6969","udp%3A%2F%2Fexodus.desync.com%3A6969"],"infoHash":"a4a1a50b4f0ec9114d77cd6a12147c07b01f4b5a","infoHashBuffer":{"type":"Buffer","data":[164,161,165,11,79,14,201,17,77,119,205,106,18,20,124,7,176,31,75,90]},"announce":[],"urlList":[]}}