{"title":"Dirty Blonde MILFs [VodRip].mp4","uid":7919826,"size":845267017,"categoryP":"porn","categoryS":"movies","magnet":"?xt=urn:btih:bd66aab52a461e66da3a943c986a0634c678c387&amp;dn=Dirty+Blonde+MILFs+%5BVodRip%5D.mp4&amp;tr=udp%3A%2F%2Ftracker.openbittorrent.com%3A80&amp;tr=udp%3A%2F%2Fopen.demonii.com%3A1337&amp;tr=udp%3A%2F%2Ftracker.coppersurfer.tk%3A6969&amp;tr=udp%3A%2F%2Fexodus.desync.com%3A6969","seeders":0,"leechers":1,"uploader":"SplashPt","files":4,"time":1355451065,"description":"Dirty Blonde MILFs [VodRip].mp4\n\nAnthony Hardwood, Kris Knight, Holly, Joey, Georgia Peach, Tommy, Justin, Jeannie Marie\n\nAnal, Older, MILF / Cougar, Blondes, Hardcore, All Sex\n\nScreens:\n &lt;a href=&quot;\nhttp://www.tinypix.me/viewer.php?file=1neyvf2bbk.jpg&quot; rel=&quot;nofollow&quot; target=&quot;_NEW&quot;&gt;\nhttp://www.tinypix.me/viewer.php?file=1neyvf2bbk.jpg&lt;/a&gt;\n &lt;a href=&quot;\nhttp://www.tinypix.me/viewer.php?file=ghf6qjighd.jpg&quot; rel=&quot;nofollow&quot; target=&quot;_NEW&quot;&gt;\nhttp://www.tinypix.me/viewer.php?file=ghf6qjighd.jpg&lt;/a&gt;\n &lt;a href=&quot;\nhttp://www.tinypix.me/viewer.php?file=w2w1ew6ji9.jpg&quot; rel=&quot;nofollow&quot; target=&quot;_NEW&quot;&gt;\nhttp://www.tinypix.me/viewer.php?file=w2w1ew6ji9.jpg&lt;/a&gt;\n &lt;a href=&quot;\nhttp://www.tinypix.me/viewer.php?file=rr7d9vugw3.jpg&quot; rel=&quot;nofollow&quot; target=&quot;_NEW&quot;&gt;\nhttp://www.tinypix.me/viewer.php?file=rr7d9vugw3.jpg&lt;/a&gt;\n &lt;a href=&quot;\nhttp://www.tinypix.me/viewer.php?file=lii6ww8bgj.jpg&quot; rel=&quot;nofollow&quot; target=&quot;_NEW&quot;&gt;\nhttp://www.tinypix.me/viewer.php?file=lii6ww8bgj.jpg&lt;/a&gt;\n","torrent":{"xt":"urn:btih:bd66aab52a461e66da3a943c986a0634c678c387","amp;dn":"Dirty+Blonde+MILFs+%5BVodRip%5D.mp4","amp;tr":["udp%3A%2F%2Ftracker.openbittorrent.com%3A80","udp%3A%2F%2Fopen.demonii.com%3A1337","udp%3A%2F%2Ftracker.coppersurfer.tk%3A6969","udp%3A%2F%2Fexodus.desync.com%3A6969"],"infoHash":"bd66aab52a461e66da3a943c986a0634c678c387","infoHashBuffer":{"type":"Buffer","data":[189,102,170,181,42,70,30,102,218,58,148,60,152,106,6,52,198,120,195,135]},"announce":[],"urlList":[]}}