{"title":"Horror Movie pack [Andazu]","uid":7942850,"size":3660429176,"categoryP":"video","categoryS":"movies","magnet":"?xt=urn:btih:f4d6d7344a587deb0f97e4d8f972c1c8cde5e2a7&amp;dn=Horror+Movie+pack+%5BAndazu%5D&amp;tr=udp%3A%2F%2Ftracker.openbittorrent.com%3A80&amp;tr=udp%3A%2F%2Fopen.demonii.com%3A1337&amp;tr=udp%3A%2F%2Ftracker.coppersurfer.tk%3A6969&amp;tr=udp%3A%2F%2Fexodus.desync.com%3A6969","seeders":0,"leechers":0,"uploader":"thepun1sher","files":6,"time":1356039109,"description":"info coming","torrent":{"xt":"urn:btih:f4d6d7344a587deb0f97e4d8f972c1c8cde5e2a7","amp;dn":"Horror+Movie+pack+%5BAndazu%5D","amp;tr":["udp%3A%2F%2Ftracker.openbittorrent.com%3A80","udp%3A%2F%2Fopen.demonii.com%3A1337","udp%3A%2F%2Ftracker.coppersurfer.tk%3A6969","udp%3A%2F%2Fexodus.desync.com%3A6969"],"infoHash":"f4d6d7344a587deb0f97e4d8f972c1c8cde5e2a7","infoHashBuffer":{"type":"Buffer","data":[244,214,215,52,74,88,125,235,15,151,228,216,249,114,193,200,205,229,226,167]},"announce":[],"urlList":[]}}