{"title":"[MilfsLikeItBig] Amber Lynn (Centerfold Me Over / 19.12.2012)","uid":7937494,"size":2776242731,"categoryP":"porn","categoryS":"hd___movies","magnet":"?xt=urn:btih:fc54a1be70b1c2966a195501fc35fcafe3324e4a&amp;dn=%5BMilfsLikeItBig%5D+Amber+Lynn+%28Centerfold+Me+Over+%2F+19.12.2012%29&amp;tr=udp%3A%2F%2Ftracker.openbittorrent.com%3A80&amp;tr=udp%3A%2F%2Fopen.demonii.com%3A1337&amp;tr=udp%3A%2F%2Ftracker.coppersurfer.tk%3A6969&amp;tr=udp%3A%2F%2Fexodus.desync.com%3A6969","seeders":0,"leechers":1,"uploader":"chkm8te","files":1,"time":1355899389,"description":"[MilfsLikeItBig] Amber Lynn (Centerfold Me Over / 19.12.2012)\n\nPhotographer Manuel is Stuck, and Badly wants to be hit with a surge of creativity. Amber Wants to be HIS Intern, but as soon as she bends over Mr. Ferrara sees all the inspiration he needs. He convinces Amber to be HIS hot muse, and soon the Camera Is not the Only thing Flashing\n\nScreens: &lt;a href=&quot;\nhttp://xxxhost.me/viewer.php?file=pc0g5fpoqscqed1ceakk.jpg&quot; rel=&quot;nofollow&quot; target=&quot;_NEW&quot;&gt;\nhttp://xxxhost.me/viewer.php?file=pc0g5fpoqscqed1ceakk.jpg&lt;/a&gt;\n &lt;a href=&quot;\nhttp://xxxhost.me/viewer.php?file=kj6my9sjatoacq0ce1gs.jpg&quot; rel=&quot;nofollow&quot; target=&quot;_NEW&quot;&gt;\nhttp://xxxhost.me/viewer.php?file=kj6my9sjatoacq0ce1gs.jpg&lt;/a&gt;","torrent":{"xt":"urn:btih:fc54a1be70b1c2966a195501fc35fcafe3324e4a","amp;dn":"%5BMilfsLikeItBig%5D+Amber+Lynn+%28Centerfold+Me+Over+%2F+19.12.2012%29","amp;tr":["udp%3A%2F%2Ftracker.openbittorrent.com%3A80","udp%3A%2F%2Fopen.demonii.com%3A1337","udp%3A%2F%2Ftracker.coppersurfer.tk%3A6969","udp%3A%2F%2Fexodus.desync.com%3A6969"],"infoHash":"fc54a1be70b1c2966a195501fc35fcafe3324e4a","infoHashBuffer":{"type":"Buffer","data":[252,84,161,190,112,177,194,150,106,25,85,1,252,53,252,175,227,50,78,74]},"announce":[],"urlList":[]}}